client/__init__.py
client/client/__init__.py
client/client/client.py
client/client/launcher.py
client/client/client/__init__.py
client/client/client/add_contact.py
client/client/client/database.py
client/client/client/del_contact.py
client/client/client/main_window.py
client/client/client/main_window_conv.py
client/client/client/start_dialog.py
client/client/client/transport.py
client/client/common/__init__.py
client/client/common/decor.py
client/client/common/deskriptors.py
client/client/common/errors.py
client/client/common/metaclases.py
client/client/common/utils.py
client/client/common/variables.py
client/client/doc/__init__.py
client/client/doc/source/__init__.py
client/client/doc/source/conf.py
client/client/logs/__init__.py
client/client/logs/config_client_log.py
client/client/logs/config_server_log.py
client/client/unit_tests/__init__.py
client/client/unit_tests/test_client.py
client/client/unit_tests/test_server.py
client/client/unit_tests/test_utils.py
my_mess_proj_client-0.0.1.dist-info/METADATA
my_mess_proj_client-0.0.1.dist-info/WHEEL
my_mess_proj_client-0.0.1.dist-info/top_level.txt
my_mess_proj_client-0.0.1.dist-info/RECORD
