Metadata-Version: 2.1
Name: my-mess-proj-client
Version: 0.0.1
Summary: my_mess_proj_client
Home-page: UNKNOWN
Author: Sergey Petin
Author-email: pillager@bk.ru
License: UNKNOWN
Platform: UNKNOWN
Requires-Dist: PyQt5
Requires-Dist: sqlalchemy
Requires-Dist: pycryptodomex
